brazilcep/__init__.py
brazilcep/__version__.py
brazilcep/apicep.py
brazilcep/client.py
brazilcep/exceptions.py
brazilcep/opencep.py
brazilcep/py.typed
brazilcep/utils.py
brazilcep/viacep.py
brazilcep-7.0.0.dist-info/licenses/LICENSE
brazilcep-7.0.0.dist-info/METADATA
brazilcep-7.0.0.dist-info/WHEEL
brazilcep-7.0.0.dist-info/top_level.txt
brazilcep-7.0.0.dist-info/RECORD
