Metadata-Version: 2.4
Name: brazilcep
Version: 7.0.0
Summary: Minimalist and easy-to-use Python library designed to query CEP (Postal Address Code) data
Author-email: Michell Stuttgart <michellstut@gmail.com>
License: 
Project-URL: Documentation, https://brazilcep.readthedocs.io/index.html
Project-URL: Repository, https://github.com/mstuttgart/brazilcep
Project-URL: Tracker, https://github.com/mstuttgart/brazilcep/issues
Project-URL: Changelog, https://github.com/mstuttgart/brazilcep/blob/main/CHANGELOG
Classifier: Development Status :: 5 - Production/Stable
Classifier: Intended Audience :: Developers
Classifier: License :: OSI Approved :: MIT License
Classifier: Operating System :: OS Independent
Classifier: Programming Language :: Python
Classifier: Programming Language :: Python :: 3
Classifier: Programming Language :: Python :: 3 :: Only
Classifier: Programming Language :: Python :: 3.9
Classifier: Programming Language :: Python :: 3.10
Classifier: Programming Language :: Python :: 3.11
Classifier: Programming Language :: Python :: 3.12
Classifier: Programming Language :: Python :: 3.13
Classifier: Topic :: Software Development :: Build Tools
Classifier: Topic :: Software Development :: Libraries
Classifier: Topic :: Software Development :: Libraries :: Python Modules
Classifier: Natural Language :: English
Classifier: Natural Language :: Portuguese (Brazilian)
Requires-Python: >=3.9
License-File: LICENSE
Requires-Dist: requests>=2.28.2
Requires-Dist: aiohttp>=3.8.1
Provides-Extra: dev
Requires-Dist: tox>=4.23.2; extra == "dev"
Requires-Dist: pytest>=7.3.1; extra == "dev"
Requires-Dist: pytest-asyncio; extra == "dev"
Requires-Dist: mypy<1.5,>=1.0; extra == "dev"
Requires-Dist: types-requests; extra == "dev"
Requires-Dist: requests-mock>=1.10.0; extra == "dev"
Requires-Dist: black<24.0,>=23.0; extra == "dev"
Requires-Dist: isort<5.13,>=5.12; extra == "dev"
Requires-Dist: pre-commit>=4.0.1; extra == "dev"
Requires-Dist: python-dotenv; extra == "dev"
Requires-Dist: ruff; extra == "dev"
Requires-Dist: ipdb; extra == "dev"
Provides-Extra: coverage
Requires-Dist: coveralls>=3.3.1; extra == "coverage"
Requires-Dist: pytest-cov>=4.0.0; extra == "coverage"
Requires-Dist: requests-mock>=1.10.0; extra == "coverage"
Requires-Dist: codecov-cli>=2.0.15; extra == "coverage"
Provides-Extra: docs
Requires-Dist: Sphinx<8,>=6; extra == "docs"
Requires-Dist: readme-renderer==43; extra == "docs"
Requires-Dist: myst-parser<2.1,>=1.0; extra == "docs"
Requires-Dist: sphinx-copybutton==0.5.2; extra == "docs"
Requires-Dist: sphinx-autobuild==2021.3.14; extra == "docs"
Requires-Dist: sphinx-autodoc-typehints==1.23.3; extra == "docs"
Provides-Extra: build
Requires-Dist: build==1.2.2.post1; extra == "build"
Dynamic: license-file
